mig_dx_api/__init__.py
mig_dx_api/_client.py
mig_dx_api/_config.py
mig_dx_api/_dataset.py
mig_dx_api/_installation.py
mig_dx_api/_models.py
mig_dx_api/_protocols.py
mig_dx_api-0.2.10.dist-info/METADATA
mig_dx_api-0.2.10.dist-info/WHEEL
mig_dx_api-0.2.10.dist-info/licenses/LICENSE
mig_dx_api-0.2.10.dist-info/RECORD
