Metadata-Version: 2.4
Name: mig-dx-api
Version: 0.2.10
Summary: Dataset Exchange API Client Library
License-Expression: MIT
License-File: LICENSE
Classifier: License :: OSI Approved :: MIT License
Requires-Python: >=3.10
Requires-Dist: aiofiles>=24.1.0
Requires-Dist: httpx>=0.27.2
Requires-Dist: loguru>=0.7.2
Requires-Dist: pydantic-settings>=2.5.2
Requires-Dist: pydantic>=2.9.2
Requires-Dist: pyjwt[crypto]>=2.9.0
